coca_pytorch/__init__.py
coca_pytorch/coca_pytorch.py
CoCa_pytorch-0.1.0.dist-info/LICENSE
CoCa_pytorch-0.1.0.dist-info/METADATA
CoCa_pytorch-0.1.0.dist-info/WHEEL
CoCa_pytorch-0.1.0.dist-info/top_level.txt
CoCa_pytorch-0.1.0.dist-info/RECORD
