Metadata-Version: 2.1
Name: CoCa-pytorch
Version: 0.1.0
Summary: CoCa, Contrastive Captioners are Image-Text Foundation Models - Pytorch
Home-page: https://github.com/lucidrains/CoCa-pytorch
Author: Phil Wang
Author-email: lucidrains@gmail.com
License: MIT
Keywords: artificial intelligence,deep learning,transformers,attention mechanism,contrastive learning,multimodal
Classifier: Development Status :: 4 - Beta
Classifier: Intended Audience :: Developers
Classifier: Topic :: Scientific/Engineering :: Artificial Intelligence
Classifier: License :: OSI Approved :: MIT License
Classifier: Programming Language :: Python :: 3.6
License-File: LICENSE
Requires-Dist: einops >=0.4
Requires-Dist: torch >=1.6
